README.md
setup.py
ihatefacebook/__init__.py
ihatefacebook/__main__.py
ihatefacebook/cli.py
ihatefacebook/helpers.py
ihatefacebook/logger.py
ihatefacebook/messages.py
ihatefacebook/paths.py
ihatefacebook/scraper.py
ihatefacebook.egg-info/PKG-INFO
ihatefacebook.egg-info/SOURCES.txt
ihatefacebook.egg-info/dependency_links.txt
ihatefacebook.egg-info/entry_points.txt
ihatefacebook.egg-info/requires.txt
ihatefacebook.egg-info/top_level.txt
ihatefacebook/facebook/__init__.py
ihatefacebook/facebook/event.py
ihatefacebook/facebook/page.py