Metadata-Version: 2.1
Name: ihatefacebook
Version: 0.5
Summary: Get notified by email whenever a Facebook page adds a new event.
Home-page: https://github.com/hot3eed/ihatefacebook
Author: Abdelrahman Eid
Author-email: hot3eed@gmail.com
License: Apache License 2.0
Platform: UNKNOWN
Requires-Python: >=3.3
